jupyterpool/__init__.py
jupyterpool/__main__.py
jupyterpool/_version.py
jupyterpool/application.py
jupyterpool/application_base.py
jupyterpool/serverapplication.py
jupyterpool/handlers/__init__.py
jupyterpool/handlers/base.py
jupyterpool/handlers/config/__init__.py
jupyterpool/handlers/config/handler.py
jupyterpool/handlers/echo/__init__.py
jupyterpool/handlers/echo/handler.py
jupyterpool/handlers/index/__init__.py
jupyterpool/handlers/index/handler.py
jupyterpool/handlers/ping/__init__.py
jupyterpool/handlers/ping/handler.py
jupyterpool/handlers/pool/__init__.py
jupyterpool/handlers/pool/handler.py
jupyterpool/handlers/proxy/__init__.py
jupyterpool/handlers/proxy/handler.py
jupyterpool/handlers/relay/__init__.py
jupyterpool/handlers/relay/handler.py
jupyterpool/kernels/__init__.py
jupyterpool/kernels/async_utils.py
jupyterpool/kernels/client_helper.py
jupyterpool/kernels/limited.py
jupyterpool/kernels/main.py
jupyterpool/kernels/mapping.py
jupyterpool/kernels/mapping_sync.py
jupyterpool/kernels/poolapp.py
jupyterpool/kernels/pooled.py
jupyterpool/kernels/pooled_sync.py
jupyterpool/kernels/py_snippets.py
jupyterpool/kernels/tests/__init__.py
jupyterpool/kernels/tests/conftest.py
jupyterpool/kernels/tests/test_in_server.py
jupyterpool/kernels/tests/test_initialize.py
jupyterpool/kernels/tests/test_limited_manager.py
jupyterpool/kernels/tests/test_limited_manager_sync.py
jupyterpool/kernels/tests/test_mapping.py
jupyterpool/kernels/tests/test_mapping_sync.py
jupyterpool/kernels/tests/test_pooled_manager.py
jupyterpool/kernels/tests/test_pooled_manager_sync.py
jupyterpool/kernels/tests/test_update.py
jupyterpool/kernels/tests/utils.py
jupyterpool/kernels/tests/utils_sync.py
jupyterpool/static/README.md
jupyterpool/templates/index.html
jupyterpool-0.0.6.data/data/etc/jupyter/jupyter_notebook_config.d/jupyterpool.json
jupyterpool-0.0.6.data/data/etc/jupyter/jupyter_server_config.d/jupyterpool.json
jupyterpool-0.0.6.dist-info/METADATA
jupyterpool-0.0.6.dist-info/WHEEL
jupyterpool-0.0.6.dist-info/entry_points.txt
jupyterpool-0.0.6.dist-info/licenses/LICENSE
jupyterpool-0.0.6.dist-info/RECORD
