Metadata-Version: 2.1
Name: jupyterpool
Version: 0.0.6
Summary: 🪐 🎱 Jupyterpool.
Project-URL: Homepage, https://github.com/datalayer/jupyterpool
Project-URL: Bug Tracker, https://github.com/datalayer/jupyterpool/issues
Project-URL: Repository, https://github.com/datalayer/jupyterpool.git
Author-email: Datalayer <info@datalayer.io>
License: BSD 3-Clause License
License-File: LICENSE
Classifier: Framework :: Jupyter
Classifier: Framework :: Jupyter :: JupyterLab
Classifier: Framework :: Jupyter :: JupyterLab :: 4
Classifier: Framework :: Jupyter :: JupyterLab :: Extensions
Classifier: Framework :: Jupyter :: JupyterLab :: Extensions :: Prebuilt
Classifier: Intended Audience :: Developers
Classifier: Intended Audience :: Science/Research
Classifier: Intended Audience :: System Administrators
Classifier: License :: OSI Approved :: BSD License
Classifier: Programming Language :: Python
Classifier: Programming Language :: Python :: 3
Classifier: Programming Language :: Python :: 3.9
Classifier: Programming Language :: Python :: 3.10
Classifier: Programming Language :: Python :: 3.11
Requires-Python: >=3.9
Requires-Dist: async-generator
Requires-Dist: datalayer
Requires-Dist: docker
Requires-Dist: jupyter-client>=7.4
Requires-Dist: jupyter-server<3,>=2
Requires-Dist: jupyterlab==4.0.10
Requires-Dist: overrides
Requires-Dist: paramiko>=2.4.0
Requires-Dist: pexpect>=4.2.0
Requires-Dist: pycryptodomex>=3.9.7
Requires-Dist: tornado>=6.2
Requires-Dist: traitlets>=5.1
Provides-Extra: dev
Requires-Dist: build; extra == 'dev'
Requires-Dist: coverage; extra == 'dev'
Requires-Dist: pre-commit; extra == 'dev'
Requires-Dist: twine; extra == 'dev'
Provides-Extra: docker
Requires-Dist: docker>=3.5.0; extra == 'docker'
Provides-Extra: k8s
Requires-Dist: jinja2>=3.1; extra == 'k8s'
Requires-Dist: kubernetes>=18.20.0; extra == 'k8s'
Provides-Extra: lint
Requires-Dist: black[jupyter]==23.9.1; extra == 'lint'
Requires-Dist: mdformat>0.7; extra == 'lint'
Requires-Dist: ruff==0.0.287; extra == 'lint'
Provides-Extra: test
Requires-Dist: coverage; extra == 'test'
Requires-Dist: docker>=3.5.0; extra == 'test'
Requires-Dist: importlib-metadata; extra == 'test'
Requires-Dist: jinja2>=3.1; extra == 'test'
Requires-Dist: kubernetes>=18.20.0; extra == 'test'
Requires-Dist: mock; extra == 'test'
Requires-Dist: pre-commit; extra == 'test'
Requires-Dist: pytest; extra == 'test'
Requires-Dist: pytest-asyncio; extra == 'test'
Requires-Dist: pytest-cov; extra == 'test'
Requires-Dist: pytest-jupyter; extra == 'test'
Requires-Dist: pytest-jupyter[server]>=0.4; extra == 'test'
Requires-Dist: pytest-timeout; extra == 'test'
Requires-Dist: pytest-tornasync; extra == 'test'
Requires-Dist: yarn-api-client; extra == 'test'
Provides-Extra: yarn
Requires-Dist: yarn-api-client; extra == 'yarn'
